{
  "id": "7502c54d-e4ab-4da9-81a1-8a10e2f26500",
  "name": "Roller Coaster Expanded",
  "authors": [
    "TheRealJonCross"
  ],
  "coordinates": [
    -2375.514,
    -1971.6543,
    15.9362
  ],
  "yaw": 83.4341,
  "nexus_id": "20487",
  "category": "location-overhaul",
  "description": "Once the Pacifica Gonks rebooted the Malls power for the Movie Theatre, it was only a matter of time until they discovered the Roller Coaster out back........This Expanded Roller Coaster is now a Front for Eddies, Packed with Npcs Standing In-Line and Sitting around the Pavilion. Courtesy the Gangs of Pacifica!",
  "tags": []
}
